bf_sdk_gateway_python/__init__.py
bf_sdk_gateway_python/client.py
bf_sdk_gateway_python/exceptions.py
bf_sdk_gateway_python/utils.py
tests/__init__.py
tests/test_client.py
bf_sdk_gateway_python-0.1.0.dist-info/LICENSE
bf_sdk_gateway_python-0.1.0.dist-info/METADATA
bf_sdk_gateway_python-0.1.0.dist-info/WHEEL
bf_sdk_gateway_python-0.1.0.dist-info/top_level.txt
bf_sdk_gateway_python-0.1.0.dist-info/RECORD
