Metadata-Version: 2.1
Name: bf-sdk-gateway-python
Version: 0.1.0
Summary: SDK para integração com o gateway de pagamentos bemfácil®
Home-page: https://github.com/bemfacil/bf_gateway_sdk_python
Author: Daniel Lima do Nascimento
Author-email: daniel.nascimento@bemfacil.com.br
License: UNKNOWN
Platform: UNKNOWN
Classifier: Programming Language :: Python :: 3
Classifier: License :: OSI Approved :: MIT License
Classifier: Operating System :: OS Independent
Requires-Python: >=3.6
License-File: LICENSE
Requires-Dist: requests
